education_math_homework_generator/__init__.py
education_math_homework_generator/gen_add_subtract.py
education_math_homework_generator/gen_clock.py
education_math_homework_generator/gen_measurement.py
education_math_homework_generator/gen_number_line.py
education_math_homework_generator/gen_table.py
education_math_homework_generator/setup.py
education_math_homework_generator/util.py
education_math_homework_generator-0.2.0.dist-info/AUTHORS.rst
education_math_homework_generator-0.2.0.dist-info/LICENSE
education_math_homework_generator-0.2.0.dist-info/METADATA
education_math_homework_generator-0.2.0.dist-info/WHEEL
education_math_homework_generator-0.2.0.dist-info/entry_points.txt
education_math_homework_generator-0.2.0.dist-info/top_level.txt
education_math_homework_generator-0.2.0.dist-info/RECORD
