Metadata-Version: 2.1
Name: education-math-homework-generator
Version: 0.2.0
Summary: Simple, scalable addition and subtraction homework generator using python and latex to create clean pdfs for early childhood 
Home-page: https://github.com/physbean/education_math_homework_generator
Author: Michael Shawn Marshall
Author-email: physbean@gmail.com
License: MIT license
Keywords: education_math_homework_generator
Platform: UNKNOWN
Classifier: Development Status :: 2 - Pre-Alpha
Classifier: Intended Audience :: Developers
Classifier: License :: OSI Approved :: MIT License
Classifier: Natural Language :: English
Classifier: Programming Language :: Python :: 3
Classifier: Programming Language :: Python :: 3.5
Classifier: Programming Language :: Python :: 3.6
Classifier: Programming Language :: Python :: 3.7
Classifier: Programming Language :: Python :: 3.8
Requires-Python: >=3.5
